xchainpy2_utils/__init__.py
xchainpy2_utils/amount.py
xchainpy2_utils/asset.py
xchainpy2_utils/async_utils.py
xchainpy2_utils/chain.py
xchainpy2_utils/consts.py
xchainpy2_utils/dates.py
xchainpy2_utils/decimals.py
xchainpy2_utils/format.py
xchainpy2_utils/math.py
xchainpy2_utils/seqs.py
xchainpy2_utils/testing_utils.py
xchainpy2_utils/type_hint.py
xchainpy2_utils/util.py
xchainpy2_utils/versions.py
xchainpy2_utils/tests/__init__.py
xchainpy2_utils/tests/test_amount.py
xchainpy2_utils/tests/test_asset.py
xchainpy2_utils/tests/test_async.py
xchainpy2_utils/tests/test_crypto_amount.py
xchainpy2_utils/tests/test_decimals.py
xchainpy2_utils/tests/test_money_format.py
xchainpy2_utils/tests/test_utils.py
xchainpy2_utils-0.0.29.dist-info/licenses/LICENSE
xchainpy2_utils-0.0.29.dist-info/METADATA
xchainpy2_utils-0.0.29.dist-info/WHEEL
xchainpy2_utils-0.0.29.dist-info/top_level.txt
xchainpy2_utils-0.0.29.dist-info/RECORD
